mcp_gen/__init__.py
mcp_gen/cli.py
mcp_gen/schemas.py
mcp_gen/template_engine.py
mcp_gen/validator.py
mcp_gen-0.1.0.dist-info/licenses/LICENSE
mcp_gen-0.1.0.dist-info/METADATA
mcp_gen-0.1.0.dist-info/WHEEL
mcp_gen-0.1.0.dist-info/entry_points.txt
mcp_gen-0.1.0.dist-info/top_level.txt
mcp_gen-0.1.0.dist-info/RECORD
