Metadata-Version: 2.4
Name: mcp-gen
Version: 0.1.0
Summary: YAML-based Model Context Protocol MCP configuration generator with template interpolation and secret management
Author: Jon Staples
Classifier: Development Status :: 3 - Alpha
Classifier: Intended Audience :: Developers
Classifier: License :: OSI Approved :: MIT License
Classifier: Operating System :: OS Independent
Classifier: Programming Language :: Python :: 3
Classifier: Programming Language :: Python :: 3.8
Classifier: Programming Language :: Python :: 3.9
Classifier: Programming Language :: Python :: 3.10
Classifier: Programming Language :: Python :: 3.11
Classifier: Programming Language :: Python :: 3.12
Requires-Python: >=3.8
License-File: LICENSE
Requires-Dist: PyYAML>=6.0
Requires-Dist: Jinja2>=3.0
Requires-Dist: Click>=8.0
Requires-Dist: jsonschema>=4.0
Provides-Extra: dev
Requires-Dist: pytest>=7.0; extra == "dev"
Requires-Dist: pytest-cov>=4.0; extra == "dev"
Requires-Dist: black>=23.0; extra == "dev"
Requires-Dist: flake8>=6.0; extra == "dev"
Dynamic: license-file
